spiderpy3/__init__.py
spiderpy3/dataclasses/__init__.py
spiderpy3/dataclasses/account_dataclass.py
spiderpy3/dbs/__init__.py
spiderpy3/dbs/db.py
spiderpy3/dbs/mongo_db.py
spiderpy3/dbs/mysql_db.py
spiderpy3/dbs/redis_db.py
spiderpy3/enums/__init__.py
spiderpy3/enums/data_status_enum.py
spiderpy3/exceptions.py
spiderpy3/items/__init__.py
spiderpy3/items/field.py
spiderpy3/items/item.py
spiderpy3/mixins/__init__.py
spiderpy3/mixins/dp.py
spiderpy3/mixins/model.py
spiderpy3/mixins/protocol.py
spiderpy3/models/__init__.py
spiderpy3/models/sqlalchemy_model.py
spiderpy3/objects/__init__.py
spiderpy3/objects/dp_handler.py
spiderpy3/objects/dp_object.py
spiderpy3/objects/dp_task.py
spiderpy3/objects/handler.py
spiderpy3/objects/login.py
spiderpy3/objects/object.py
spiderpy3/objects/spider.py
spiderpy3/objects/task.py
spiderpy3/objects/verify.py
spiderpy3/resources/spiderpy3/utils/verify/slide/1737356729443.json
spiderpy3/resources/spiderpy3/utils/verify/slide/1737356734891.json
spiderpy3/resources/spiderpy3/utils/verify/slide/1737356740435.json
spiderpy3/resources/spiderpy3/utils/verify/slide/1737430486782.json
spiderpy3/resources/spiderpy3/utils/verify/slide/1737430492423.json
spiderpy3/resources/spiderpy3/utils/verify/slide/1737430497878.json
spiderpy3/resources/spiderpy3/utils/verify/slide/1737430503134.json
spiderpy3/resources/spiderpy3/utils/verify/slide/1737430508871.json
spiderpy3/resources/spiderpy3/utils/verify/slide/1737430514758.json
spiderpy3/resources/spiderpy3/utils/verify/slide/1737430520054.json
spiderpy3/resources/spiderpy3/utils/verify/slide/1737430525078.json
spiderpy3/resources/spiderpy3/utils/verify/slide/1737430536790.json
spiderpy3/resources/spiderpy3/utils/verify/slide/1737430542046.json
spiderpy3/resources/spiderpy3/utils/verify/slide/1737430553278.json
spiderpy3/resources/spiderpy3/utils/verify/slide/1737430558094.json
spiderpy3/resources/spiderpy3/utils/verify/slide/1737430563926.json
spider_py3-0.1.0.20250201.dist-info/LICENSE
spider_py3-0.1.0.20250201.dist-info/METADATA
spider_py3-0.1.0.20250201.dist-info/WHEEL
spider_py3-0.1.0.20250201.dist-info/RECORD
