Metadata-Version: 2.3
Name: spider-py3
Version: 0.1.0.20250201
Summary: 
Author: mathewgeola
Author-email: mathewgeola@gmail.com
Requires-Python: >=3.10,<3.13
Classifier: Programming Language :: Python :: 3
Classifier: Programming Language :: Python :: 3.10
Classifier: Programming Language :: Python :: 3.11
Classifier: Programming Language :: Python :: 3.12
Requires-Dist: aiohttp (>=3.11.11,<4.0.0)
Requires-Dist: arrow (>=1.3.0,<2.0.0)
Requires-Dist: bs4 (>=0.0.2,<0.0.3)
Requires-Dist: colorlog (>=6.9.0,<7.0.0)
Requires-Dist: cx-oracle (>=8.3.0,<9.0.0)
Requires-Dist: ddddocr (>=1.5.6,<2.0.0)
Requires-Dist: drissionpage (>=4.1.0.17,<5.0.0.0)
Requires-Dist: fake-useragent (>=2.0.3,<3.0.0)
Requires-Dist: furl (>=2.1.3,<3.0.0)
Requires-Dist: htmlmin (>=0.1.12,<0.2.0)
Requires-Dist: httpx (>=0.28.1,<0.29.0)
Requires-Dist: jinja2 (>=3.1.5,<4.0.0)
Requires-Dist: jsonpath (>=0.82.2,<0.83.0)
Requires-Dist: matplotlib (>=3.10.0,<4.0.0)
Requires-Dist: numpy (>=2.2.1,<3.0.0)
Requires-Dist: opencv-python (>=4.10.0.84,<5.0.0.0)
Requires-Dist: openpyxl (>=3.1.5,<4.0.0)
Requires-Dist: oss2 (>=2.19.1,<3.0.0)
Requires-Dist: pandas (>=2.2.3,<3.0.0)
Requires-Dist: parsel (>=1.9.1,<2.0.0)
Requires-Dist: pika (>=1.3.2,<2.0.0)
Requires-Dist: pillow (>=11.1.0,<12.0.0)
Requires-Dist: py-mini-racer (>=0.6.0,<0.7.0)
Requires-Dist: pycryptodome (>=3.21.0,<4.0.0)
Requires-Dist: pyexecjs (>=1.5.1,<2.0.0)
Requires-Dist: pymongo (>=4.10.1,<5.0.0)
Requires-Dist: pymysql (>=1.1.1,<2.0.0)
Requires-Dist: pyyaml (>=6.0.2,<7.0.0)
Requires-Dist: redis (>=5.2.1,<6.0.0)
Requires-Dist: requests (>=2.32.3,<3.0.0)
Requires-Dist: socksio (>=1.0.0,<2.0.0)
Requires-Dist: sqlalchemy (>=2.0.36,<3.0.0)
Requires-Dist: sqlparse (>=0.5.3,<0.6.0)
Requires-Dist: tenacity (>=9.0.0,<10.0.0)
Requires-Dist: tldextract (>=5.1.3,<6.0.0)
Requires-Dist: tqdm (>=4.67.1,<5.0.0)
Requires-Dist: ujson (>=5.10.0,<6.0.0)
Requires-Dist: xlrd (>=2.0.1,<3.0.0)
Requires-Dist: xlwt (>=1.3.0,<2.0.0)
